HuaxiaZhichengPmpRenzhengKaoshiYubeiKechengHoulijunFix1/README.md
HuaxiaZhichengPmpRenzhengKaoshiYubeiKechengHoulijunFix1/__init__.py
HuaxiaZhichengPmpRenzhengKaoshiYubeiKechengHoulijunFix1/__main__.py
HuaxiaZhichengPmpRenzhengKaoshiYubeiKechengHoulijunFix1/file.pdf
HuaxiaZhichengPmpRenzhengKaoshiYubeiKechengHoulijunFix1/index.html
huaxia_zhicheng_pmp_renzheng_kaoshi_yubei_kecheng_houlijun_fix1-2025.3.25.0.dist-info/METADATA
huaxia_zhicheng_pmp_renzheng_kaoshi_yubei_kecheng_houlijun_fix1-2025.3.25.0.dist-info/WHEEL
huaxia_zhicheng_pmp_renzheng_kaoshi_yubei_kecheng_houlijun_fix1-2025.3.25.0.dist-info/entry_points.txt
huaxia_zhicheng_pmp_renzheng_kaoshi_yubei_kecheng_houlijun_fix1-2025.3.25.0.dist-info/top_level.txt
huaxia_zhicheng_pmp_renzheng_kaoshi_yubei_kecheng_houlijun_fix1-2025.3.25.0.dist-info/RECORD
